Workbook

Sheet Note di lettura
B2: PIANO DEI CONTI POPOLATO - Srl manifatturiera/commerciale - Esercizio 2026 - Stile Zucchetti AGO
B5: AZIENDA DI ESEMPIO
B6: Srl manifatturiera/commerciale, fatturato annuo circa 4 milioni di euro, esercizio in utile.
B7: Capitale sociale 100.000 euro, ~25 dipendenti (costo personale ~840.000), parco immobilizzato
B8: consistente (fabbricato di proprieta', macchinari, attrezzature). Indebitamento bancario di
B9: medio termine per circa 460.000 euro (mutui), oltre a finanziamento soci di 100.000 euro.
B11: STRUTTURA DEL PIANO DEI CONTI
B12: Codifica gerarchica a 3 livelli, formato MMM.CCC.SSSS:
B13: - Mastro : 3 cifre (es. 010 - Immobilizzazioni Immateriali)
B14: - Conto : 3 cifre (es. 010.005 - Costi di impianto e ampliamento)
B15: - Sottoconto: 4 cifre (es. 010.005.0001 - Costi di costituzione)
B16: Le scritture in prima nota si imputano SEMPRE ai sottoconti (foglie operative).
... B57: - 'Legenda' : abbreviazioni e principi OIC

Sheet Piano dei Conti
A1: Codice | B1: Livello | C1: Descrizione | D1: Sezione CEE | E1: Natura | F1: D/A | G1: Saldo Dare | H1: Saldo Avere | I1: Note
A2: 010 | B2: Mastro | C2: IMMOBILIZZAZIONI IMMATERIALI | D2: B.I | E2: Attivo Patrimoniale | G2: =SUMIFS($G$2:$G$455,$A$2:$A$455,"010.*",$B$2:$B$455,"Sottoconto") -> 232000 | H2: =SUMIFS($H$2:$H$455,$A$2:$A$455,"010.*",$B$2:$B$455,"Sottoconto") -> 125000
A3: 010.005 | B3: Conto | C3: Costi di impianto e di ampliamento | D3: B.I.1 | G3: =SUMIFS($G$2:$G$455,$A$2:$A$455,"010.005.*",$B$2:$B$455,"Sottoconto") -> 12000 | H3: =SUMIFS($H$2:$H$455,$A$2:$A$455,"010.005.*",$B$2:$B$455,"Sottoconto") -> 12000
A4: 010.005.0001 | B4: Sottoconto | C4: Costi di costituzione | D4: B.I.1 | E4: Attivo Patrimoniale | F4: D | G4: 8000 | H4: 0 | I4: Amm.to max 5 anni - art. 2426 c.c.
A5: 010.005.0002 | B5: Sottoconto | C5: Costi di ampliamento | D5: B.I.1 | E5: Attivo Patrimoniale | F5: D | G5: 4000 | H5: 0
A6: 010.005.9001 | B6: Sottoconto | C6: F.do amm.to costi di impianto e amplto | D6: B.I.1 | E6: Rettifica (fondo) | F6: A | G6: 0 | H6: 12000 | I6: Fondo rettificativo
A7: 010.010 | B7: Conto | C7: Costi di sviluppo | D7: B.I.2 | G7: =SUMIFS($G$2:$G$455,$A$2:$A$455,"010.010.*",$B$2:$B$455,"Sottoconto") -> 0 | H7: =SUMIFS($H$2:$H$455,$A$2:$A$455,"010.010.*",$B$2:$B$455,"Sottoconto") -> 0
A8: 010.010.0001 | B8: Sottoconto | C8: Costi di sviluppo capitalizzati | D8: B.I.2 | E8: Attivo Patrimoniale | F8: D | G8: 0 | H8: 0 | I8: Solo se ricorrono condizioni OIC 24
A9: 010.010.9001 | B9: Sottoconto | C9: F.do amm.to costi di sviluppo | D9: B.I.2 | E9: Rettifica (fondo) | F9: A | G9: 0 | H9: 0
A10: 010.015 | B10: Conto | C10: Diritti di brevetto industriale | D10: B.I.3 | G10: =SUMIFS($G$2:$G$455,$A$2:$A$455,"010.015.*",$B$2:$B$455,"Sottoconto") -> 30000 | H10: =SUMIFS($H$2:$H$455,$A$2:$A$455,"010.015.*",$B$2:$B$455,"Sottoconto") -> 12000
A11: 010.015.0001 | B11: Sottoconto | C11: Brevetti industriali | D11: B.I.3 | E11: Attivo Patrimoniale | F11: D | G11: 0 | H11: 0
A12: 010.015.0002 | B12: Sottoconto | C12: Software applicativo di proprieta' | D12: B.I.3 | E12: Attivo Patrimoniale | F12: D | G12: 30000 | H12: 0
A13: 010.015.0003 | B13: Sottoconto | C13: Diritti d'autore | D13: B.I.3 | E13: Attivo Patrimoniale | F13: D | G13: 0 | H13: 0
A14: 010.015.9001 | B14: Sottoconto | C14: F.do amm.to brevetti | D14: B.I.3 | E14: Rettifica (fondo) | F14: A | G14: 0 | H14: 0
A15: 010.015.9002 | B15: Sottoconto | C15: F.do amm.to software | D15: B.I.3 | E15: Rettifica (fondo) | F15: A | G15: 0 | H15: 12000
A16: 010.020 | B16: Conto | C16: Concessioni, licenze, marchi e simili | D16: B.I.4 | G16: =SUMIFS($G$2:$G$455,$A$2:$A$455,"010.020.*",$B$2:$B$455,"Sottoconto") -> 50000 | H16: =SUMIFS($H$2:$H$455,$A$2:$A$455,"010.020.*",$B$2:$B$455,"Sottoconto") -> 25000
A17: 010.020.0001 | B17: Sottoconto | C17: Marchi | D17: B.I.4 | E17: Attivo Patrimoniale | F17: D | G17: 50000 | H17: 0
A18: 010.020.0002 | B18: Sottoconto | C18: Licenze d'uso software (capitalizzate) | D18: B.I.4 | E18: Attivo Patrimoniale | F18: D | G18: 0 | H18: 0
A19: 010.020.0003 | B19: Sottoconto | C19: Concessioni | D19: B.I.4 | E19: Attivo Patrimoniale | F19: D | G19: 0 | H19: 0
A20: 010.020.9001 | B20: Sottoconto | C20: F.do amm.to marchi | D20: B.I.4 | E20: Rettifica (fondo) | F20: A | G20: 0 | H20: 25000
A21: 010.020.9002 | B21: Sottoconto | C21: F.do amm.to licenze software | D21: B.I.4 | E21: Rettifica (fondo) | F21: A | G21: 0 | H21: 0
A22: 010.020.9003 | B22: Sottoconto | C22: F.do amm.to concessioni | D22: B.I.4 | E22: Rettifica (fondo) | F22: A | G22: 0 | H22: 0
A23: 010.025 | B23: Conto | C23: Avviamento | D23: B.I.5 | G23: =SUMIFS($G$2:$G$455,$A$2:$A$455,"010.025.*",$B$2:$B$455,"Sottoconto") -> 100000 | H23: =SUMIFS($H$2:$H$455,$A$2:$A$455,"010.025.*",$B$2:$B$455,"Sottoconto") -> 60000
A24: 010.025.0001 | B24: Sottoconto | C24: Avviamento | D24: B.I.5 | E24: Attivo Patrimoniale | F24: D | G24: 100000 | H24: 0 | I24: Solo se acquisito a titolo oneroso
A25: 010.025.9001 | B25: Sottoconto | C25: F.do amm.to avviamento | D25: B.I.5 | E25: Rettifica (fondo) | F25: A | G25: 0 | H25: 60000 | I25: Vita utile, max 10 anni in via residuale
A26: 010.030 | B26: Conto | C26: Immob. immateriali in corso e acconti | D26: B.I.6 | G26: =SUMIFS($G$2:$G$455,$A$2:$A$455,"010.030.*",$B$2:$B$455,"Sottoconto") -> 0 | H26: =SUMIFS($H$2:$H$455,$A$2:$A$455,"010.030.*",$B$2:$B$455,"Sottoconto") -> 0
A27: 010.030.0001 | B27: Sottoconto | C27: Immobilizzazioni immateriali in corso | D27: B.I.6 | E27: Attivo Patrimoniale | F27: D | G27: 0 | H27: 0
A28: 010.030.0002 | B28: Sottoconto | C28: Acconti su immob. immateriali | D28: B.I.6 | E28: Attivo Patrimoniale | F28: D | G28: 0 | H28: 0
A29: 010.035 | B29: Conto | C29: Altre immobilizzazioni immateriali | D29: B.I.7 | G29: =SUMIFS($G$2:$G$455,$A$2:$A$455,"010.035.*",$B$2:$B$455,"Sottoconto") -> 40000 | H29: =SUMIFS($H$2:$H$455,$A$2:$A$455,"010.035.*",$B$2:$B$455,"Sottoconto") -> 16000
A30: 010.035.0001 | B30: Sottoconto | C30: Migliorie su beni di terzi | D30: B.I.7 | E30: Attivo Patrimoniale | F30: D | G30: 40000 | H30: 0 | I30: Lavori su immobile in locazione
A31: 010.035.0002 | B31: Sottoconto | C31: Spese pluriennali diverse | D31: B.I.7 | E31: Attivo Patrimoniale | F31: D | G31: 0 | H31: 0
A32: 010.035.9001 | B32: Sottoconto | C32: F.do amm.to migliorie su beni di terzi | D32: B.I.7 | E32: Rettifica (fondo) | F32: A | G32: 0 | H32: 16000
A33: 010.035.9002 | B33: Sottoconto | C33: F.do amm.to altre immob. immateriali | D33: B.I.7 | E33: Rettifica (fondo) | F33: A | G33: 0 | H33: 0
A34: 020 | B34: Mastro | C34: IMMOBILIZZAZIONI MATERIALI | D34: B.II | E34: Attivo Patrimoniale | G34: =SUMIFS($G$2:$G$455,$A$2:$A$455,"020.*",$B$2:$B$455,"Sottoconto") -> 1825000 | H34: =SUMIFS($H$2:$H$455,$A$2:$A$455,"020.*",$B$2:$B$455,"Sottoconto") -> 736500
A35: 020.005 | B35: Conto | C35: Terreni e fabbricati | D35: B.II.1 | G35: =SUMIFS($G$2:$G$455,$A$2:$A$455,"020.005.*",$B$2:$B$455,"Sottoconto") -> 800000 | H35: =SUMIFS($H$2:$H$455,$A$2:$A$455,"020.005.*",$B$2:$B$455,"Sottoconto") -> 240000
A36: 020.005.0001 | B36: Sottoconto | C36: Terreni | D36: B.II.1 | E36: Attivo Patrimoniale | F36: D | G36: 200000 | H36: 0 | I36: Non ammortizzabili - OIC 16
A37: 020.005.0002 | B37: Sottoconto | C37: Fabbricati industriali | D37: B.II.1 | E37: Attivo Patrimoniale | F37: D | G37: 600000 | H37: 0
A38: 020.005.0003 | B38: Sottoconto | C38: Fabbricati civili strumentali | D38: B.II.1 | E38: Attivo Patrimoniale | F38: D | G38: 0 | H38: 0
A39: 020.005.0004 | B39: Sottoconto | C39: Costruzioni leggere | D39: B.II.1 | E39: Attivo Patrimoniale | F39: D | G39: 0 | H39: 0
A40: 020.005.9002 | B40: Sottoconto | C40: F.do amm.to fabbricati industriali | D40: B.II.1 | E40: Rettifica (fondo) | F40: A | G40: 0 | H40: 240000
A41: 020.005.9003 | B41: Sottoconto | C41: F.do amm.to fabbricati civili | D41: B.II.1 | E41: Rettifica (fondo) | F41: A | G41: 0 | H41: 0
A42: 020.005.9004 | B42: Sottoconto | C42: F.do amm.to costruzioni leggere | D42: B.II.1 | E42: Rettifica (fondo) | F42: A | G42: 0 | H42: 0
A43: 020.010 | B43: Conto | C43: Impianti e macchinario | D43: B.II.2 | G43: =SUMIFS($G$2:$G$455,$A$2:$A$455,"020.010.*",$B$2:$B$455,"Sottoconto") -> 750000 | H43: =SUMIFS($H$2:$H$455,$A$2:$A$455,"020.010.*",$B$2:$B$455,"Sottoconto") -> 335000
A44: 020.010.0001 | B44: Sottoconto | C44: Impianti generici | D44: B.II.2 | E44: Attivo Patrimoniale | F44: D | G44: 0 | H44: 0
A45: 020.010.0002 | B45: Sottoconto | C45: Impianti specifici | D45: B.II.2 | E45: Attivo Patrimoniale | F45: D | G45: 350000 | H45: 0
A46: 020.010.0003 | B46: Sottoconto | C46: Macchinari | D46: B.II.2 | E46: Attivo Patrimoniale | F46: D | G46: 400000 | H46: 0
A47: 020.010.0004 | B47: Sottoconto | C47: Impianti di telecomunicazione | D47: B.II.2 | E47: Attivo Patrimoniale | F47: D | G47: 0 | H47: 0
A48: 020.010.0005 | B48: Sottoconto | C48: Impianti fotovoltaici | D48: B.II.2 | E48: Attivo Patrimoniale | F48: D | G48: 0 | H48: 0
A49: 020.010.9001 | B49: Sottoconto | C49: F.do amm.to impianti generici | D49: B.II.2 | E49: Rettifica (fondo) | F49: A | G49: 0 | H49: 0
A50: 020.010.9002 | B50: Sottoconto | C50: F.do amm.to impianti specifici | D50: B.II.2 | E50: Rettifica (fondo) | F50: A | G50: 0 | H50: 175000
A51: 020.010.9003 | B51: Sottoconto | C51: F.do amm.to macchinari | D51: B.II.2 | E51: Rettifica (fondo) | F51: A | G51: 0 | H51: 160000
A52: 020.010.9004 | B52: Sottoconto | C52: F.do amm.to impianti telecomunicazione | D52: B.II.2 | E52: Rettifica (fondo) | F52: A | G52: 0 | H52: 0
A53: 020.010.9005 | B53: Sottoconto | C53: F.do amm.to impianti fotovoltaici | D53: B.II.2 | E53: Rettifica (fondo) | F53: A | G53: 0 | H53: 0
A54: 020.015 | B54: Conto | C54: Attrezzature industriali e commerciali | D54: B.II.3 | G54: =SUMIFS($G$2:$G$455,$A$2:$A$455,"020.015.*",$B$2:$B$455,"Sottoconto") -> 80000 | H54: =SUMIFS($H$2:$H$455,$A$2:$A$455,"020.015.*",$B$2:$B$455,"Sottoconto") -> 56000
A55: 020.015.0001 | B55: Sottoconto | C55: Attrezzature industriali | D55: B.II.3 | E55: Attivo Patrimoniale | F55: D | G55: 80000 | H55: 0
A56: 020.015.0002 | B56: Sottoconto | C56: Attrezzature commerciali | D56: B.II.3 | E56: Attivo Patrimoniale | F56: D | G56: 0 | H56: 0
A57: 020.015.0003 | B57: Sottoconto | C57: Attrezzatura varia minuta | D57: B.II.3 | E57: Attivo Patrimoniale | F57: D | G57: 0 | H57: 0
A58: 020.015.9001 | B58: Sottoconto | C58: F.do amm.to attrezzature industriali | D58: B.II.3 | E58: Rettifica (fondo) | F58: A | G58: 0 | H58: 56000
A59: 020.015.9002 | B59: Sottoconto | C59: F.do amm.to attrezzature commerciali | D59: B.II.3 | E59: Rettifica (fondo) | F59: A | G59: 0 | H59: 0
A60: 020.015.9003 | B60: Sottoconto | C60: F.do amm.to attrezzatura varia minuta | D60: B.II.3 | E60: Rettifica (fondo) | F60: A | G60: 0 | H60: 0
A61: 020.020 | B61: Conto | C61: Altri beni | D61: B.II.4 | G61: =SUMIFS($G$2:$G$455,$A$2:$A$455,"020.020.*",$B$2:$B$455,"Sottoconto") -> 195000 | H61: =SUMIFS($H$2:$H$455,$A$2:$A$455,"020.020.*",$B$2:$B$455,"Sottoconto") -> 105500
A62: 020.020.0001 | B62: Sottoconto | C62: Mobili e arredi ufficio | D62: B.II.4 | E62: Attivo Patrimoniale | F62: D | G62: 30000 | H62: 0
A63: 020.020.0002 | B63: Sottoconto | C63: Macchine ufficio elettroniche | D63: B.II.4 | E63: Attivo Patrimoniale | F63: D | G63: 0 | H63: 0
A64: 020.020.0003 | B64: Sottoconto | C64: Hardware (PC, server, stampanti) | D64: B.II.4 | E64: Attivo Patrimoniale | F64: D | G64: 25000 | H64: 0
A65: 020.020.0004 | B65: Sottoconto | C65: Autovetture | D65: B.II.4 | E65: Attivo Patrimoniale | F65: D | G65: 60000 | H65: 0 | I65: Limiti deduc. art. 164 TUIR
A66: 020.020.0005 | B66: Sottoconto | C66: Autocarri e veicoli commerciali | D66: B.II.4 | E66: Attivo Patrimoniale | F66: D | G66: 80000 | H66: 0
A67: 020.020.0006 | B67: Sottoconto | C67: Telefoni cellulari aziendali | D67: B.II.4 | E67: Attivo Patrimoniale | F67: D | G67: 0 | H67: 0 | I67: Deduc. 80% - art. 102 TUIR
A68: 020.020.0007 | B68: Sottoconto | C68: Beni inferiori a 516,46 euro | D68: B.II.4 | E68: Attivo Patrimoniale | F68: D | G68: 0 | H68: 0 | I68: Deduc. integrale possibile
A69: 020.020.9001 | B69: Sottoconto | C69: F.do amm.to mobili e arredi | D69: B.II.4 | E69: Rettifica (fondo) | F69: A | G69: 0 | H69: 18000
A70: 020.020.9002 | B70: Sottoconto | C70: F.do amm.to macchine ufficio | D70: B.II.4 | E70: Rettifica (fondo) | F70: A | G70: 0 | H70: 0
A71: 020.020.9003 | B71: Sottoconto | C71: F.do amm.to hardware | D71: B.II.4 | E71: Rettifica (fondo) | F71: A | G71: 0 | H71: 17500
A72: 020.020.9004 | B72: Sottoconto | C72: F.do amm.to autovetture | D72: B.II.4 | E72: Rettifica (fondo) | F72: A | G72: 0 | H72: 30000
A73: 020.020.9005 | B73: Sottoconto | C73: F.do amm.to autocarri | D73: B.II.4 | E73: Rettifica (fondo) | F73: A | G73: 0 | H73: 40000
A74: 020.020.9006 | B74: Sottoconto | C74: F.do amm.to telefoni cellulari | D74: B.II.4 | E74: Rettifica (fondo) | F74: A | G74: 0 | H74: 0
A75: 020.025 | B75: Conto | C75: Immob. materiali in corso e acconti | D75: B.II.5 | G75: =SUMIFS($G$2:$G$455,$A$2:$A$455,"020.025.*",$B$2:$B$455,"Sottoconto") -> 0 | H75: =SUMIFS($H$2:$H$455,$A$2:$A$455,"020.025.*",$B$2:$B$455,"Sottoconto") -> 0
A76: 020.025.0001 | B76: Sottoconto | C76: Immobilizzazioni materiali in corso | D76: B.II.5 | E76: Attivo Patrimoniale | F76: D | G76: 0 | H76: 0
A77: 020.025.0002 | B77: Sottoconto | C77: Acconti su immob. materiali | D77: B.II.5 | E77: Attivo Patrimoniale | F77: D | G77: 0 | H77: 0
A78: 030 | B78: Mastro | C78: IMMOBILIZZAZIONI FINANZIARIE | D78: B.III | E78: Attivo Patrimoniale | G78: =SUMIFS($G$2:$G$455,$A$2:$A$455,"030.*",$B$2:$B$455,"Sottoconto") -> 25000 | H78: =SUMIFS($H$2:$H$455,$A$2:$A$455,"030.*",$B$2:$B$455,"Sottoconto") -> 0
A79: 030.005 | B79: Conto | C79: Partecipazioni | D79: B.III.1 | G79: =SUMIFS($G$2:$G$455,$A$2:$A$455,"030.005.*",$B$2:$B$455,"Sottoconto") -> 25000 | H79: =SUMIFS($H$2:$H$455,$A$2:$A$455,"030.005.*",$B$2:$B$455,"Sottoconto") -> 0
A80: 030.005.0001 | B80: Sottoconto | C80: Partecipazioni in imprese controllate | D80: B.III.1.a | E80: Attivo Patrimoniale | F80: D | G80: 0 | H80: 0
A81: 030.005.0002 | B81: Sottoconto | C81: Partecipazioni in imprese collegate | D81: B.III.1.b | E81: Attivo Patrimoniale | F81: D | G81: 0 | H81: 0
A82: 030.005.0003 | B82: Sottoconto | C82: Partecipazioni in imprese controllanti | D82: B.III.1.c | E82: Attivo Patrimoniale | F82: D | G82: 0 | H82: 0
A83: 030.005.0004 | B83: Sottoconto | C83: Part. in imprese sotto controllo controllanti | D83: B.III.1.d-bis | E83: Attivo Patrimoniale | F83: D | G83: 0 | H83: 0 | I83: Introdotto da D.Lgs. 139/2015
A84: 030.005.0005 | B84: Sottoconto | C84: Partecipazioni in altre imprese | D84: B.III.1.d | E84: Attivo Patrimoniale | F84: D | G84: 25000 | H84: 0
A85: 030.010 | B85: Conto | C85: Crediti finanziari immobilizzati | D85: B.III.2 | G85: =SUMIFS($G$2:$G$455,$A$2:$A$455,"030.010.*",$B$2:$B$455,"Sottoconto") -> 0 | H85: =SUMIFS($H$2:$H$455,$A$2:$A$455,"030.010.*",$B$2:$B$455,"Sottoconto") -> 0 | I85: Esigibili oltre l'esercizio
A86: 030.010.0001 | B86: Sottoconto | C86: Crediti v/imprese controllate | D86: B.III.2.a | E86: Attivo Patrimoniale | F86: D | G86: 0 | H86: 0
A87: 030.010.0002 | B87: Sottoconto | C87: Crediti v/imprese collegate | D87: B.III.2.b | E87: Attivo Patrimoniale | F87: D | G87: 0 | H87: 0
A88: 030.010.0003 | B88: Sottoconto | C88: Crediti v/imprese controllanti | D88: B.III.2.c | E88: Attivo Patrimoniale | F88: D | G88: 0 | H88: 0
A89: 030.010.0004 | B89: Sottoconto | C89: Crediti v/imprese sotto controllo controllanti | D89: B.III.2.d-bis | E89: Attivo Patrimoniale | F89: D | G89: 0 | H89: 0
A90: 030.010.0005 | B90: Sottoconto | C90: Crediti v/altri | D90: B.III.2.d | E90: Attivo Patrimoniale | F90: D | G90: 0 | H90: 0
A91: 030.015 | B91: Conto | C91: Altri titoli | D91: B.III.3 | G91: =SUMIFS($G$2:$G$455,$A$2:$A$455,"030.015.*",$B$2:$B$455,"Sottoconto") -> 0 | H91: =SUMIFS($H$2:$H$455,$A$2:$A$455,"030.015.*",$B$2:$B$455,"Sottoconto") -> 0
A92: 030.015.0001 | B92: Sottoconto | C92: Altri titoli immobilizzati | D92: B.III.3 | E92: Attivo Patrimoniale | F92: D | G92: 0 | H92: 0
A93: 030.020 | B93: Conto | C93: Strumenti finanziari derivati attivi | D93: B.III.4 | G93: =SUMIFS($G$2:$G$455,$A$2:$A$455,"030.020.*",$B$2:$B$455,"Sottoconto") -> 0 | H93: =SUMIFS($H$2:$H$455,$A$2:$A$455,"030.020.*",$B$2:$B$455,"Sottoconto") -> 0 | I93: Introdotto da D.Lgs. 139/2015
A94: 030.020.0001 | B94: Sottoconto | C94: Strumenti fin. derivati attivi immob. | D94: B.III.4 | E94: Attivo Patrimoniale | F94: D | G94: 0 | H94: 0
A95: 040 | B95: Mastro | C95: RIMANENZE | D95: C.I | E95: Attivo Patrimoniale | G95: =SUMIFS($G$2:$G$455,$A$2:$A$455,"040.*",$B$2:$B$455,"Sottoconto") -> 390000 | H95: =SUMIFS($H$2:$H$455,$A$2:$A$455,"040.*",$B$2:$B$455,"Sottoconto") -> 0
A96: 040.005 | B96: Conto | C96: Materie prime, sussidiarie e di consumo | D96: C.I.1 | G96: =SUMIFS($G$2:$G$455,$A$2:$A$455,"040.005.*",$B$2:$B$455,"Sottoconto") -> 180000 | H96: =SUMIFS($H$2:$H$455,$A$2:$A$455,"040.005.*",$B$2:$B$455,"Sottoconto") -> 0
A97: 040.005.0001 | B97: Sottoconto | C97: Rimanenze materie prime | D97: C.I.1 | E97: Attivo Patrimoniale | F97: D | G97: 180000 | H97: 0
A98: 040.005.0002 | B98: Sottoconto | C98: Rimanenze materie sussidiarie | D98: C.I.1 | E98: Attivo Patrimoniale | F98: D | G98: 0 | H98: 0
A99: 040.005.0003 | B99: Sottoconto | C99: Rimanenze materiali di consumo | D99: C.I.1 | E99: Attivo Patrimoniale | F99: D | G99: 0 | H99: 0
A100: 040.010 | B100: Conto | C100: Prodotti in corso di lav. e semilavorati | D100: C.I.2 | G100: =SUMIFS($G$2:$G$455,$A$2:$A$455,"040.010.*",$B$2:$B$455,"Sottoconto") -> 50000 | H100: =SUMIFS($H$2:$H$455,$A$2:$A$455,"040.010.*",$B$2:$B$455,"Sottoconto") -> 0
...

Sheet Bilancio Verifica
A1: BILANCIO DI VERIFICA AL 31/12/2026 - Sintesi per Mastro
A2: Mastro | B2: Descrizione | C2: Saldo Dare | D2: Saldo Avere | E2: Saldo Netto
A3: 010 | B3: IMMOBILIZZAZIONI IMMATERIALI | C3: ='Piano dei Conti'!G2 -> 232000 | D3: ='Piano dei Conti'!H2 -> 125000 | E3: =C3-D3 -> 107000
A4: 020 | B4: IMMOBILIZZAZIONI MATERIALI | C4: ='Piano dei Conti'!G34 -> 1825000 | D4: ='Piano dei Conti'!H34 -> 736500 | E4: =C4-D4 -> 1088500
A5: 030 | B5: IMMOBILIZZAZIONI FINANZIARIE | C5: ='Piano dei Conti'!G78 -> 25000 | D5: ='Piano dei Conti'!H78 -> 0 | E5: =C5-D5 -> 25000
A6: 040 | B6: RIMANENZE | C6: ='Piano dei Conti'!G95 -> 390000 | D6: ='Piano dei Conti'!H95 -> 0 | E6: =C6-D6 -> 390000
A7: 050 | B7: CREDITI DELL'ATTIVO CIRCOLANTE | C7: ='Piano dei Conti'!G110 -> 1157000 | D7: ='Piano dei Conti'!H110 -> 60000 | E7: =C7-D7 -> 1097000
A8: 060 | B8: ATTIVITA' FINANZIARIE NON IMMOBILIZZATE | C8: ='Piano dei Conti'!G146 -> 0 | D8: ='Piano dei Conti'!H146 -> 0 | E8: =C8-D8 -> 0
A9: 070 | B9: DISPONIBILITA' LIQUIDE | C9: ='Piano dei Conti'!G158 -> 132300 | D9: ='Piano dei Conti'!H158 -> 0 | E9: =C9-D9 -> 132300
A10: 080 | B10: RATEI E RISCONTI ATTIVI | C10: ='Piano dei Conti'!G171 -> 8000 | D10: ='Piano dei Conti'!H171 -> 0 | E10: =C10-D10 -> 8000
A11: 100 | B11: PATRIMONIO NETTO | C11: ='Piano dei Conti'!G177 -> 0 | D11: ='Piano dei Conti'!H177 -> 499300 | E11: =C11-D11 -> -499300
A12: 110 | B12: FONDI PER RISCHI E ONERI | C12: ='Piano dei Conti'!G204 -> 0 | D12: ='Piano dei Conti'!H204 -> 45000 | E12: =C12-D12 -> -45000
A13: 120 | B13: TRATTAMENTO DI FINE RAPPORTO | C13: ='Piano dei Conti'!G217 -> 0 | D13: ='Piano dei Conti'!H217 -> 145000 | E13: =C13-D13 -> -145000
A14: 130 | B14: DEBITI | C14: ='Piano dei Conti'!G220 -> 0 | D14: ='Piano dei Conti'!H220 -> 1761800 | E14: =C14-D14 -> -1761800
A15: 180 | B15: RATEI E RISCONTI PASSIVI | C15: ='Piano dei Conti'!G280 -> 0 | D15: ='Piano dei Conti'!H280 -> 8000 | E15: =C15-D15 -> -8000
A16: 300 | B16: VALORE DELLA PRODUZIONE | C16: ='Piano dei Conti'!G286 -> 25000 | D16: ='Piano dei Conti'!H286 -> 4053000 | E16: =C16-D16 -> -4028000
A17: 200 | B17: COSTI DELLA PRODUZIONE | C17: ='Piano dei Conti'!G314 -> 3462100 | D17: ='Piano dei Conti'!H314 -> 40000 | E17: =C17-D17 -> 3422100
A18: 400 | B18: PROVENTI E ONERI FINANZIARI | C18: ='Piano dei Conti'!G410 -> 0 | D18: ='Piano dei Conti'!H410 -> 5800 | E18: =C18-D18 -> -5800
A19: 410 | B19: INTERESSI E ALTRI ONERI FINANZIARI | C19: ='Piano dei Conti'!G424 -> 56000 | D19: ='Piano dei Conti'!H424 -> 0 | E19: =C19-D19 -> 56000
A20: 420 | B20: RETTIFICHE DI VALORE ATTIVITA' E PASS. FIN. | C20: ='Piano dei Conti'!G434 -> 0 | D20: ='Piano dei Conti'!H434 -> 0 | E20: =C20-D20 -> 0
A21: 480 | B21: IMPOSTE SUL REDDITO DELL'ESERCIZIO | C21: ='Piano dei Conti'!G445 -> 170500 | D21: ='Piano dei Conti'!H445 -> 3500 | E21: =C21-D21 -> 167000
A22: 500 | B22: RISULTATO DELL'ESERCIZIO | C22: ='Piano dei Conti'!G453 -> 0 | D22: ='Piano dei Conti'!H453 -> 0 | E22: =C22-D22 -> 0
B23: TOTALE BILANCIO DI VERIFICA | C23: =SUM(C3:C22) -> 7482900 | D23: =SUM(D3:D22) -> 7482900 | E23: =C23-D23 -> 0
B24: QUADRATURA | C24: =C23-D23 -> 0 | D24: =IF(ROUND(C23-D23,2)=0,"QUADRATO","SBILANCIO") -> QUADRATO

Sheet SP CEE Valorizzato
A1: STATO PATRIMONIALE CIVILISTICO (artt. 2424 c.c.) - VALORIZZATO al 31/12/2026
A3: ATTIVO
A4: A) CREDITI VERSO SOCI PER VERSAMENTI ANCORA DOVUTI | B4: 0
A5: B) IMMOBILIZZAZIONI
A6: I. Immobilizzazioni immateriali | B6: =SUMIFS('Piano dei Conti'!G2:G455,'Piano dei Conti'!A2:A455,"010.*",'Piano dei Conti'!B2:B455,"Sottoconto")-SUMIFS('Piano dei Conti'!H2:H455,'Piano dei Conti'!A2:A455,"010.*",'Piano dei Conti'!B2:B455,"Sottoconto") -> 107000
A7: 1) Costi di impianto e di ampliamento | B7: =SUMIFS('Piano dei Conti'!G2:G455,'Piano dei Conti'!A2:A455,"010.005.*",'Piano dei Conti'!B2:B455,"Sottoconto")-SUMIFS('Piano dei Conti'!H2:H455,'Piano dei Conti'!A2:A455,"010.005.*",'Piano dei Conti'!B2:B455,"Sottoconto") -> 0
A8: 3) Diritti brev. ind., utilizzo opere ingegno | B8: =SUMIFS('Piano dei Conti'!G2:G455,'Piano dei Conti'!A2:A455,"010.015.*",'Piano dei Conti'!B2:B455,"Sottoconto")-SUMIFS('Piano dei Conti'!H2:H455,'Piano dei Conti'!A2:A455,"010.015.*",'Piano dei Conti'!B2:B455,"Sottoconto") -> 18000
A9: 4) Concessioni, licenze, marchi e simili | B9: =SUMIFS('Piano dei Conti'!G2:G455,'Piano dei Conti'!A2:A455,"010.020.*",'Piano dei Conti'!B2:B455,"Sottoconto")-SUMIFS('Piano dei Conti'!H2:H455,'Piano dei Conti'!A2:A455,"010.020.*",'Piano dei Conti'!B2:B455,"Sottoconto") -> 25000
A10: 5) Avviamento | B10: =SUMIFS('Piano dei Conti'!G2:G455,'Piano dei Conti'!A2:A455,"010.025.*",'Piano dei Conti'!B2:B455,"Sottoconto")-SUMIFS('Piano dei Conti'!H2:H455,'Piano dei Conti'!A2:A455,"010.025.*",'Piano dei Conti'!B2:B455,"Sottoconto") -> 40000
A11: 7) Altre immobilizzazioni immateriali | B11: =SUMIFS('Piano dei Conti'!G2:G455,'Piano dei Conti'!A2:A455,"010.035.*",'Piano dei Conti'!B2:B455,"Sottoconto")-SUMIFS('Piano dei Conti'!H2:H455,'Piano dei Conti'!A2:A455,"010.035.*",'Piano dei Conti'!B2:B455,"Sottoconto") -> 24000
A12: II. Immobilizzazioni materiali | B12: =SUMIFS('Piano dei Conti'!G2:G455,'Piano dei Conti'!A2:A455,"020.*",'Piano dei Conti'!B2:B455,"Sottoconto")-SUMIFS('Piano dei Conti'!H2:H455,'Piano dei Conti'!A2:A455,"020.*",'Piano dei Conti'!B2:B455,"Sottoconto") -> 1088500
A13: 1) Terreni e fabbricati | B13: =SUMIFS('Piano dei Conti'!G2:G455,'Piano dei Conti'!A2:A455,"020.005.*",'Piano dei Conti'!B2:B455,"Sottoconto")-SUMIFS('Piano dei Conti'!H2:H455,'Piano dei Conti'!A2:A455,"020.005.*",'Piano dei Conti'!B2:B455,"Sottoconto") -> 560000
A14: 2) Impianti e macchinario | B14: =SUMIFS('Piano dei Conti'!G2:G455,'Piano dei Conti'!A2:A455,"020.010.*",'Piano dei Conti'!B2:B455,"Sottoconto")-SUMIFS('Piano dei Conti'!H2:H455,'Piano dei Conti'!A2:A455,"020.010.*",'Piano dei Conti'!B2:B455,"Sottoconto") -> 415000
A15: 3) Attrezzature industriali e commerciali | B15: =SUMIFS('Piano dei Conti'!G2:G455,'Piano dei Conti'!A2:A455,"020.015.*",'Piano dei Conti'!B2:B455,"Sottoconto")-SUMIFS('Piano dei Conti'!H2:H455,'Piano dei Conti'!A2:A455,"020.015.*",'Piano dei Conti'!B2:B455,"Sottoconto") -> 24000
A16: 4) Altri beni | B16: =SUMIFS('Piano dei Conti'!G2:G455,'Piano dei Conti'!A2:A455,"020.020.*",'Piano dei Conti'!B2:B455,"Sottoconto")-SUMIFS('Piano dei Conti'!H2:H455,'Piano dei Conti'!A2:A455,"020.020.*",'Piano dei Conti'!B2:B455,"Sottoconto") -> 89500
A17: III. Immobilizzazioni finanziarie | B17: =SUMIFS('Piano dei Conti'!G2:G455,'Piano dei Conti'!A2:A455,"030.*",'Piano dei Conti'!B2:B455,"Sottoconto")-SUMIFS('Piano dei Conti'!H2:H455,'Piano dei Conti'!A2:A455,"030.*",'Piano dei Conti'!B2:B455,"Sottoconto") -> 25000
A18: 1.d) Partecipazioni in altre imprese | B18: =SUMIFS('Piano dei Conti'!G2:G455,'Piano dei Conti'!A2:A455,"030.005.0005",'Piano dei Conti'!B2:B455,"Sottoconto")-SUMIFS('Piano dei Conti'!H2:H455,'Piano dei Conti'!A2:A455,"030.005.0005",'Piano dei Conti'!B2:B455,"Sottoconto") -> 25000
A19: Totale Immobilizzazioni (B) | B19: =B6+B12+B17 -> 1220500
A20: C) ATTIVO CIRCOLANTE
A21: I. Rimanenze | B21: =SUMIFS('Piano dei Conti'!G2:G455,'Piano dei Conti'!A2:A455,"040.*",'Piano dei Conti'!B2:B455,"Sottoconto")-SUMIFS('Piano dei Conti'!H2:H455,'Piano dei Conti'!A2:A455,"040.*",'Piano dei Conti'!B2:B455,"Sottoconto") -> 390000
A22: 1) Materie prime, sussidiarie, di consumo | B22: =SUMIFS('Piano dei Conti'!G2:G455,'Piano dei Conti'!A2:A455,"040.005.*",'Piano dei Conti'!B2:B455,"Sottoconto")-SUMIFS('Piano dei Conti'!H2:H455,'Piano dei Conti'!A2:A455,"040.005.*",'Piano dei Conti'!B2:B455,"Sottoconto") -> 180000
A23: 2) Prodotti in corso di lavorazione e semilavorati | B23: =SUMIFS('Piano dei Conti'!G2:G455,'Piano dei Conti'!A2:A455,"040.010.*",'Piano dei Conti'!B2:B455,"Sottoconto")-SUMIFS('Piano dei Conti'!H2:H455,'Piano dei Conti'!A2:A455,"040.010.*",'Piano dei Conti'!B2:B455,"Sottoconto") -> 50000
A24: 4) Prodotti finiti e merci | B24: =SUMIFS('Piano dei Conti'!G2:G455,'Piano dei Conti'!A2:A455,"040.020.*",'Piano dei Conti'!B2:B455,"Sottoconto")-SUMIFS('Piano dei Conti'!H2:H455,'Piano dei Conti'!A2:A455,"040.020.*",'Piano dei Conti'!B2:B455,"Sottoconto") -> 160000
A25: II. Crediti | B25: =SUMIFS('Piano dei Conti'!G2:G455,'Piano dei Conti'!A2:A455,"050.*",'Piano dei Conti'!B2:B455,"Sottoconto")-SUMIFS('Piano dei Conti'!H2:H455,'Piano dei Conti'!A2:A455,"050.*",'Piano dei Conti'!B2:B455,"Sottoconto") -> 1097000
A26: 1) Verso clienti (al netto fondo svalutazione) | B26: =SUMIFS('Piano dei Conti'!G2:G455,'Piano dei Conti'!A2:A455,"050.005.*",'Piano dei Conti'!B2:B455,"Sottoconto")-SUMIFS('Piano dei Conti'!H2:H455,'Piano dei Conti'!A2:A455,"050.005.*",'Piano dei Conti'!B2:B455,"Sottoconto") -> 1045000
A27: 5-bis) Crediti tributari | B27: =SUMIFS('Piano dei Conti'!G2:G455,'Piano dei Conti'!A2:A455,"050.030.*",'Piano dei Conti'!B2:B455,"Sottoconto")-SUMIFS('Piano dei Conti'!H2:H455,'Piano dei Conti'!A2:A455,"050.030.*",'Piano dei Conti'!B2:B455,"Sottoconto") -> 23500
A28: 5-ter) Imposte anticipate | B28: =SUMIFS('Piano dei Conti'!G2:G455,'Piano dei Conti'!A2:A455,"050.035.*",'Piano dei Conti'!B2:B455,"Sottoconto")-SUMIFS('Piano dei Conti'!H2:H455,'Piano dei Conti'!A2:A455,"050.035.*",'Piano dei Conti'!B2:B455,"Sottoconto") -> 18000
A29: 5-quater) Verso altri | B29: =SUMIFS('Piano dei Conti'!G2:G455,'Piano dei Conti'!A2:A455,"050.040.*",'Piano dei Conti'!B2:B455,"Sottoconto")-SUMIFS('Piano dei Conti'!H2:H455,'Piano dei Conti'!A2:A455,"050.040.*",'Piano dei Conti'!B2:B455,"Sottoconto") -> 10500
A30: IV. Disponibilita' liquide | B30: =SUMIFS('Piano dei Conti'!G2:G455,'Piano dei Conti'!A2:A455,"070.*",'Piano dei Conti'!B2:B455,"Sottoconto")-SUMIFS('Piano dei Conti'!H2:H455,'Piano dei Conti'!A2:A455,"070.*",'Piano dei Conti'!B2:B455,"Sottoconto") -> 132300
A31: 1) Depositi bancari e postali | B31: =SUMIFS('Piano dei Conti'!G2:G455,'Piano dei Conti'!A2:A455,"070.005.*",'Piano dei Conti'!B2:B455,"Sottoconto")-SUMIFS('Piano dei Conti'!H2:H455,'Piano dei Conti'!A2:A455,"070.005.*",'Piano dei Conti'!B2:B455,"Sottoconto") -> 130000
A32: 3) Denaro e valori in cassa | B32: =SUMIFS('Piano dei Conti'!G2:G455,'Piano dei Conti'!A2:A455,"070.015.*",'Piano dei Conti'!B2:B455,"Sottoconto")-SUMIFS('Piano dei Conti'!H2:H455,'Piano dei Conti'!A2:A455,"070.015.*",'Piano dei Conti'!B2:B455,"Sottoconto") -> 2300
A33: Totale Attivo Circolante (C) | B33: =B21+B25+B30 -> 1619300
A34: D) RATEI E RISCONTI ATTIVI | B34: =SUMIFS('Piano dei Conti'!G2:G455,'Piano dei Conti'!A2:A455,"080.*",'Piano dei Conti'!B2:B455,"Sottoconto")-SUMIFS('Piano dei Conti'!H2:H455,'Piano dei Conti'!A2:A455,"080.*",'Piano dei Conti'!B2:B455,"Sottoconto") -> 8000
A36: TOTALE ATTIVO | B36: =B19+B33+B34 -> 2847800
A38: PASSIVO E PATRIMONIO NETTO
A39: A) PATRIMONIO NETTO
A40: I. Capitale | B40: =SUMIFS('Piano dei Conti'!H2:H455,'Piano dei Conti'!A2:A455,"100.005.*",'Piano dei Conti'!B2:B455,"Sottoconto")-SUMIFS('Piano dei Conti'!G2:G455,'Piano dei Conti'!A2:A455,"100.005.*",'Piano dei Conti'!B2:B455,"Sottoconto") -> 100000
A41: IV. Riserva legale | B41: =SUMIFS('Piano dei Conti'!H2:H455,'Piano dei Conti'!A2:A455,"100.020.*",'Piano dei Conti'!B2:B455,"Sottoconto")-SUMIFS('Piano dei Conti'!G2:G455,'Piano dei Conti'!A2:A455,"100.020.*",'Piano dei Conti'!B2:B455,"Sottoconto") -> 20000
A42: VI. Altre riserve (straord. + vers. soci c/cap) | B42: =SUMIFS('Piano dei Conti'!H2:H455,'Piano dei Conti'!A2:A455,"100.030.*",'Piano dei Conti'!B2:B455,"Sottoconto")-SUMIFS('Piano dei Conti'!G2:G455,'Piano dei Conti'!A2:A455,"100.030.*",'Piano dei Conti'!B2:B455,"Sottoconto") -> 234000
A43: VIII. Utili (perdite) portati a nuovo | B43: =SUMIFS('Piano dei Conti'!H2:H455,'Piano dei Conti'!A2:A455,"100.040.*",'Piano dei Conti'!B2:B455,"Sottoconto")-SUMIFS('Piano dei Conti'!G2:G455,'Piano dei Conti'!A2:A455,"100.040.*",'Piano dei Conti'!B2:B455,"Sottoconto") -> 145300
A44: IX. Utile (perdita) dell'esercizio (calcolato dal CE) | B44: ='CE CEE Valorizzato'!B38 -> 388700
A45: Totale Patrimonio Netto (A) | B45: =B40+B41+B42+B43+B44 -> 888000
A46: B) FONDI PER RISCHI E ONERI | B46: =SUMIFS('Piano dei Conti'!H2:H455,'Piano dei Conti'!A2:A455,"110.*",'Piano dei Conti'!B2:B455,"Sottoconto")-SUMIFS('Piano dei Conti'!G2:G455,'Piano dei Conti'!A2:A455,"110.*",'Piano dei Conti'!B2:B455,"Sottoconto") -> 45000
A47: 2) Fondo imposte differite | B47: =SUMIFS('Piano dei Conti'!H2:H455,'Piano dei Conti'!A2:A455,"110.010.*",'Piano dei Conti'!B2:B455,"Sottoconto")-SUMIFS('Piano dei Conti'!G2:G455,'Piano dei Conti'!A2:A455,"110.010.*",'Piano dei Conti'!B2:B455,"Sottoconto") -> 12000
A48: 4) Altri fondi (manutenz., cause legali) | B48: =SUMIFS('Piano dei Conti'!H2:H455,'Piano dei Conti'!A2:A455,"110.020.*",'Piano dei Conti'!B2:B455,"Sottoconto")-SUMIFS('Piano dei Conti'!G2:G455,'Piano dei Conti'!A2:A455,"110.020.*",'Piano dei Conti'!B2:B455,"Sottoconto") -> 33000
A49: C) TRATTAMENTO DI FINE RAPPORTO | B49: =SUMIFS('Piano dei Conti'!H2:H455,'Piano dei Conti'!A2:A455,"120.*",'Piano dei Conti'!B2:B455,"Sottoconto")-SUMIFS('Piano dei Conti'!G2:G455,'Piano dei Conti'!A2:A455,"120.*",'Piano dei Conti'!B2:B455,"Sottoconto") -> 145000
A50: D) DEBITI | B50: =SUMIFS('Piano dei Conti'!H2:H455,'Piano dei Conti'!A2:A455,"130.*",'Piano dei Conti'!B2:B455,"Sottoconto")-SUMIFS('Piano dei Conti'!G2:G455,'Piano dei Conti'!A2:A455,"130.*",'Piano dei Conti'!B2:B455,"Sottoconto") -> 1761800
A51: 3) Debiti verso soci per finanziamenti | B51: =SUMIFS('Piano dei Conti'!H2:H455,'Piano dei Conti'!A2:A455,"130.010.*",'Piano dei Conti'!B2:B455,"Sottoconto")-SUMIFS('Piano dei Conti'!G2:G455,'Piano dei Conti'!A2:A455,"130.010.*",'Piano dei Conti'!B2:B455,"Sottoconto") -> 100000
A52: 4) Debiti verso banche | B52: =SUMIFS('Piano dei Conti'!H2:H455,'Piano dei Conti'!A2:A455,"130.015.*",'Piano dei Conti'!B2:B455,"Sottoconto")-SUMIFS('Piano dei Conti'!G2:G455,'Piano dei Conti'!A2:A455,"130.015.*",'Piano dei Conti'!B2:B455,"Sottoconto") -> 545000
A53: 5) Debiti verso altri finanziatori | B53: =SUMIFS('Piano dei Conti'!H2:H455,'Piano dei Conti'!A2:A455,"130.020.*",'Piano dei Conti'!B2:B455,"Sottoconto")-SUMIFS('Piano dei Conti'!G2:G455,'Piano dei Conti'!A2:A455,"130.020.*",'Piano dei Conti'!B2:B455,"Sottoconto") -> 60000
A54: 6) Acconti (clienti c/anticipi) | B54: =SUMIFS('Piano dei Conti'!H2:H455,'Piano dei Conti'!A2:A455,"130.025.*",'Piano dei Conti'!B2:B455,"Sottoconto")-SUMIFS('Piano dei Conti'!G2:G455,'Piano dei Conti'!A2:A455,"130.025.*",'Piano dei Conti'!B2:B455,"Sottoconto") -> 25000
A55: 7) Debiti verso fornitori | B55: =SUMIFS('Piano dei Conti'!H2:H455,'Piano dei Conti'!A2:A455,"130.030.*",'Piano dei Conti'!B2:B455,"Sottoconto")-SUMIFS('Piano dei Conti'!G2:G455,'Piano dei Conti'!A2:A455,"130.030.*",'Piano dei Conti'!B2:B455,"Sottoconto") -> 775000
A56: 12) Debiti tributari | B56: =SUMIFS('Piano dei Conti'!H2:H455,'Piano dei Conti'!A2:A455,"130.060.*",'Piano dei Conti'!B2:B455,"Sottoconto")-SUMIFS('Piano dei Conti'!G2:G455,'Piano dei Conti'!A2:A455,"130.060.*",'Piano dei Conti'!B2:B455,"Sottoconto") -> 130500
A57: 13) Debiti verso istituti di previdenza | B57: =SUMIFS('Piano dei Conti'!H2:H455,'Piano dei Conti'!A2:A455,"130.065.*",'Piano dei Conti'!B2:B455,"Sottoconto")-SUMIFS('Piano dei Conti'!G2:G455,'Piano dei Conti'!A2:A455,"130.065.*",'Piano dei Conti'!B2:B455,"Sottoconto") -> 39300
A58: 14) Altri debiti | B58: =SUMIFS('Piano dei Conti'!H2:H455,'Piano dei Conti'!A2:A455,"130.070.*",'Piano dei Conti'!B2:B455,"Sottoconto")-SUMIFS('Piano dei Conti'!G2:G455,'Piano dei Conti'!A2:A455,"130.070.*",'Piano dei Conti'!B2:B455,"Sottoconto") -> 87000
A59: E) RATEI E RISCONTI PASSIVI | B59: =SUMIFS('Piano dei Conti'!H2:H455,'Piano dei Conti'!A2:A455,"180.*",'Piano dei Conti'!B2:B455,"Sottoconto")-SUMIFS('Piano dei Conti'!G2:G455,'Piano dei Conti'!A2:A455,"180.*",'Piano dei Conti'!B2:B455,"Sottoconto") -> 8000
A61: TOTALE PASSIVO E PATRIMONIO NETTO | B61: =B45+B46+B49+B50+B59 -> 2847800
A63: VERIFICA: Attivo - (Passivo+PN) = | B63: =B36-B61 -> 0

Sheet CE CEE Valorizzato
A1: CONTO ECONOMICO CIVILISTICO (art. 2425 c.c.) - VALORIZZATO esercizio 2026
A3: A) VALORE DELLA PRODUZIONE
A4: 1) Ricavi delle vendite e delle prestazioni | B4: =-1*(SUMIFS('Piano dei Conti'!G2:G455,'Piano dei Conti'!A2:A455,"300.005.*",'Piano dei Conti'!B2:B455,"Sottoconto")-SUMIFS('Piano dei Conti'!H2:H455,'Piano dei Conti'!A2:A455,"300.005.*",'Piano dei Conti'!B2:B455,"Sottoconto")) -> 3925000
A5: 2) Variazioni rim. prodotti in corso, semilav., finiti | B5: =-1*(SUMIFS('Piano dei Conti'!G2:G455,'Piano dei Conti'!A2:A455,"300.010.*",'Piano dei Conti'!B2:B455,"Sottoconto")-SUMIFS('Piano dei Conti'!H2:H455,'Piano dei Conti'!A2:A455,"300.010.*",'Piano dei Conti'!B2:B455,"Sottoconto")) -> 45000
A6: 5) Altri ricavi e proventi | B6: =-1*(SUMIFS('Piano dei Conti'!G2:G455,'Piano dei Conti'!A2:A455,"300.025.*",'Piano dei Conti'!B2:B455,"Sottoconto")-SUMIFS('Piano dei Conti'!H2:H455,'Piano dei Conti'!A2:A455,"300.025.*",'Piano dei Conti'!B2:B455,"Sottoconto")) -> 58000
A7: di cui contributi in c/esercizio | B7: =-1*(SUMIFS('Piano dei Conti'!G2:G455,'Piano dei Conti'!A2:A455,"300.025.0003",'Piano dei Conti'!B2:B455,"Sottoconto")-SUMIFS('Piano dei Conti'!H2:H455,'Piano dei Conti'!A2:A455,"300.025.0003",'Piano dei Conti'!B2:B455,"Sottoconto")) -> 8000
A8: Totale A) | B8: =B4+B5+B6 -> 4028000
A10: B) COSTI DELLA PRODUZIONE
A11: 6) Costi materie prime, sussidiarie, consumo, merci | B11: =SUMIFS('Piano dei Conti'!G2:G455,'Piano dei Conti'!A2:A455,"200.005.*",'Piano dei Conti'!B2:B455,"Sottoconto")-SUMIFS('Piano dei Conti'!H2:H455,'Piano dei Conti'!A2:A455,"200.005.*",'Piano dei Conti'!B2:B455,"Sottoconto") -> 1453000
A12: 7) Costi per servizi | B12: =SUMIFS('Piano dei Conti'!G2:G455,'Piano dei Conti'!A2:A455,"200.010.*",'Piano dei Conti'!B2:B455,"Sottoconto")-SUMIFS('Piano dei Conti'!H2:H455,'Piano dei Conti'!A2:A455,"200.010.*",'Piano dei Conti'!B2:B455,"Sottoconto") -> 758000
A13: 8) Costi per godimento beni di terzi | B13: =SUMIFS('Piano dei Conti'!G2:G455,'Piano dei Conti'!A2:A455,"200.015.*",'Piano dei Conti'!B2:B455,"Sottoconto")-SUMIFS('Piano dei Conti'!H2:H455,'Piano dei Conti'!A2:A455,"200.015.*",'Piano dei Conti'!B2:B455,"Sottoconto") -> 165000
A14: 9) Costi per il personale | B14: =SUMIFS('Piano dei Conti'!G2:G455,'Piano dei Conti'!A2:A455,"200.020.*",'Piano dei Conti'!B2:B455,"Sottoconto")-SUMIFS('Piano dei Conti'!H2:H455,'Piano dei Conti'!A2:A455,"200.020.*",'Piano dei Conti'!B2:B455,"Sottoconto") -> 837000
A15: a) salari e stipendi | B15: =SUMIFS('Piano dei Conti'!G2:G455,'Piano dei Conti'!A2:A455,"200.020.0001",'Piano dei Conti'!B2:B455,"Sottoconto")-SUMIFS('Piano dei Conti'!H2:H455,'Piano dei Conti'!A2:A455,"200.020.0001",'Piano dei Conti'!B2:B455,"Sottoconto") -> 580000
A16: b) oneri sociali | B16: =SUMIFS('Piano dei Conti'!G2:G455,'Piano dei Conti'!A2:A455,"200.020.0002",'Piano dei Conti'!B2:B455,"Sottoconto")-SUMIFS('Piano dei Conti'!H2:H455,'Piano dei Conti'!A2:A455,"200.020.0002",'Piano dei Conti'!B2:B455,"Sottoconto")+SUMIFS('Piano dei Conti'!G2:G455,'Piano dei Conti'!A2:A455,"200.020.0003",'Piano dei Conti'!B2:B455,"Sottoconto")-SUMIFS('Piano dei Conti'!H2:H455,'Piano dei Conti'!A2:A455,"200.020.0003",'Piano dei Conti'!B2:B455,"Sottoconto") -> 187000
A17: c) trattamento di fine rapporto | B17: =SUMIFS('Piano dei Conti'!G2:G455,'Piano dei Conti'!A2:A455,"200.020.0004",'Piano dei Conti'!B2:B455,"Sottoconto")-SUMIFS('Piano dei Conti'!H2:H455,'Piano dei Conti'!A2:A455,"200.020.0004",'Piano dei Conti'!B2:B455,"Sottoconto") -> 42000
A18: e) altri costi | B18: =SUMIFS('Piano dei Conti'!G2:G455,'Piano dei Conti'!A2:A455,"200.020.0006",'Piano dei Conti'!B2:B455,"Sottoconto")-SUMIFS('Piano dei Conti'!H2:H455,'Piano dei Conti'!A2:A455,"200.020.0006",'Piano dei Conti'!B2:B455,"Sottoconto")+SUMIFS('Piano dei Conti'!G2:G455,'Piano dei Conti'!A2:A455,"200.020.0007",'Piano dei Conti'!B2:B455,"Sottoconto")-SUMIFS('Piano dei Conti'!H2:H455,'Piano dei Conti'!A2:A455,"200.020.0007",'Piano dei Conti'!B2:B455,"Sottoconto")+SUMIFS('Piano dei Conti'!G2:G455,'Piano dei Conti'!A2:A455,"200.020.0008",'Piano dei Conti'!B2:B455,"Sottoconto")-SUMIFS('Piano dei Conti'!H2:H455,'Piano dei Conti'!A2:A455,"200.020.0008",'Piano dei Conti'!B2:B455,"Sottoconto") -> 28000
A19: 10) Ammortamenti e svalutazioni | B19: =SUMIFS('Piano dei Conti'!G2:G455,'Piano dei Conti'!A2:A455,"200.025.*",'Piano dei Conti'!B2:B455,"Sottoconto")-SUMIFS('Piano dei Conti'!H2:H455,'Piano dei Conti'!A2:A455,"200.025.*",'Piano dei Conti'!B2:B455,"Sottoconto") -> 185000
A20: a) amm.to immob. immateriali | B20: =SUMIFS('Piano dei Conti'!G2:G455,'Piano dei Conti'!A2:A455,"200.025.0001",'Piano dei Conti'!B2:B455,"Sottoconto")-SUMIFS('Piano dei Conti'!H2:H455,'Piano dei Conti'!A2:A455,"200.025.0001",'Piano dei Conti'!B2:B455,"Sottoconto") -> 28000
A21: b) amm.to immob. materiali | B21: =SUMIFS('Piano dei Conti'!G2:G455,'Piano dei Conti'!A2:A455,"200.025.0002",'Piano dei Conti'!B2:B455,"Sottoconto")-SUMIFS('Piano dei Conti'!H2:H455,'Piano dei Conti'!A2:A455,"200.025.0002",'Piano dei Conti'!B2:B455,"Sottoconto") -> 145000
A22: d) svalutazione crediti attivo circolante | B22: =SUMIFS('Piano dei Conti'!G2:G455,'Piano dei Conti'!A2:A455,"200.025.0004",'Piano dei Conti'!B2:B455,"Sottoconto")-SUMIFS('Piano dei Conti'!H2:H455,'Piano dei Conti'!A2:A455,"200.025.0004",'Piano dei Conti'!B2:B455,"Sottoconto") -> 12000
A23: 11) Variazione rim. materie prime, sussidiarie, consumo, merci | B23: =SUMIFS('Piano dei Conti'!G2:G455,'Piano dei Conti'!A2:A455,"200.030.*",'Piano dei Conti'!B2:B455,"Sottoconto")-SUMIFS('Piano dei Conti'!H2:H455,'Piano dei Conti'!A2:A455,"200.030.*",'Piano dei Conti'!B2:B455,"Sottoconto") -> -20000
A24: 12) Accantonamenti per rischi | B24: =SUMIFS('Piano dei Conti'!G2:G455,'Piano dei Conti'!A2:A455,"200.035.*",'Piano dei Conti'!B2:B455,"Sottoconto")-SUMIFS('Piano dei Conti'!H2:H455,'Piano dei Conti'!A2:A455,"200.035.*",'Piano dei Conti'!B2:B455,"Sottoconto") -> 8000
A25: 14) Oneri diversi di gestione | B25: =SUMIFS('Piano dei Conti'!G2:G455,'Piano dei Conti'!A2:A455,"200.045.*",'Piano dei Conti'!B2:B455,"Sottoconto")-SUMIFS('Piano dei Conti'!H2:H455,'Piano dei Conti'!A2:A455,"200.045.*",'Piano dei Conti'!B2:B455,"Sottoconto") -> 36100
A26: Totale B) | B26: =B11+B12+B13+B14+B19+B23+B24+B25 -> 3422100
A28: DIFFERENZA TRA VALORE E COSTI DELLA PRODUZIONE (A-B) | B28: =B8-B26 -> 605900
A30: C) PROVENTI E ONERI FINANZIARI
A31: 16) Altri proventi finanziari | B31: =-1*(SUMIFS('Piano dei Conti'!G2:G455,'Piano dei Conti'!A2:A455,"400.010.*",'Piano dei Conti'!B2:B455,"Sottoconto")-SUMIFS('Piano dei Conti'!H2:H455,'Piano dei Conti'!A2:A455,"400.010.*",'Piano dei Conti'!B2:B455,"Sottoconto")) -> 5800
A32: 17) Interessi e altri oneri finanziari | B32: =SUMIFS('Piano dei Conti'!G2:G455,'Piano dei Conti'!A2:A455,"410.005.*",'Piano dei Conti'!B2:B455,"Sottoconto")-SUMIFS('Piano dei Conti'!H2:H455,'Piano dei Conti'!A2:A455,"410.005.*",'Piano dei Conti'!B2:B455,"Sottoconto") -> 56000
A33: Totale C) | B33: =B31-B32 -> -50200
A35: RISULTATO PRIMA DELLE IMPOSTE (A-B+/-C) | B35: =B28+B33 -> 555700
A36: 20) Imposte sul reddito (correnti, differite, anticipate) | B36: =SUMIFS('Piano dei Conti'!G2:G455,'Piano dei Conti'!A2:A455,"480.005.*",'Piano dei Conti'!B2:B455,"Sottoconto")-SUMIFS('Piano dei Conti'!H2:H455,'Piano dei Conti'!A2:A455,"480.005.*",'Piano dei Conti'!B2:B455,"Sottoconto") -> 167000
A38: 21) UTILE (PERDITA) DELL'ESERCIZIO | B38: =B35-B36 -> 388700

Sheet Schema SP CEE
A1: Voce di bilancio | B1: Riferimento PdC
A2: ATTIVO
A3: A) Crediti verso soci per versamenti ancora dovuti
A4: B) IMMOBILIZZAZIONI
A5: I - Immobilizzazioni immateriali | B5: Mastro 010
A6: II - Immobilizzazioni materiali | B6: Mastro 020
A7: III - Immobilizzazioni finanziarie | B7: Mastro 030
A8: C) ATTIVO CIRCOLANTE
A9: I - Rimanenze | B9: Mastro 040
A10: II - Crediti | B10: Mastro 050
A11: III - Attivita' finanziarie non immobilizzate | B11: Mastro 060
A12: IV - Disponibilita' liquide | B12: Mastro 070
A13: D) RATEI E RISCONTI ATTIVI | B13: Mastro 080
A15: PASSIVO
A16: A) PATRIMONIO NETTO | B16: Mastro 100
A17: B) FONDI PER RISCHI E ONERI | B17: Mastro 110
A18: C) TRATTAMENTO DI FINE RAPPORTO | B18: Mastro 120
A19: D) DEBITI | B19: Mastro 130
A20: E) RATEI E RISCONTI PASSIVI | B20: Mastro 180

Sheet Legenda
A1: Termine / sigla | B1: Spiegazione
A2: LIVELLO
A3: Mastro | B3: Livello 1 - aggregazione di alto livello (es. 'Immob. Materiali'). Sintetico, non si movimenta direttamente.
A4: Conto | B4: Livello 2 - sottoinsieme tematico di un mastro. Sintetico, non si movimenta direttamente.
A5: Sottoconto | B5: Livello 3 - foglia operativa, e' qui che si registrano le scritture in prima nota.
A7: NATURA
A8: Attivo Patrim. | B8: Voce dello Stato Patrimoniale - sezione Attivo (saldo Dare).
A9: Passivo Patrim. | B9: Voce dello Stato Patrimoniale - sezione Passivo (saldo Avere).
A10: Patrimonio Netto | B10: Capitale e riserve della societa' (saldo Avere; perdite hanno saldo Dare).
A11: Costo (CE) | B11: Voce del Conto Economico - costo (saldo Dare).
A12: Ricavo (CE) | B12: Voce del Conto Economico - ricavo o provento (saldo Avere).
A13: Rettifica (fondo) | B13: Conto rettificativo dell'attivo (es. fondo amm.to). Saldo Avere ma classificato in detrazione dell'attivo.
A15: D/A
A16: D | B16: Saldo normale in DARE (attivita', costi).
A17: A | B17: Saldo normale in AVERE (passivita', PN, ricavi, fondi).
A19: RIFERIMENTI NORMATIVI / OIC
A20: Codice Civile | B20: Artt. 2424 (SP), 2425 (CE), 2426 (criteri valutazione), 2427 (nota integrativa).
A21: D.Lgs. 139/2015 | B21: Riforma del bilancio: eliminazione conti d'ordine, introduzione strumenti derivati.
A22: OIC 9 | B22: Svalutazioni delle immobilizzazioni materiali e immateriali.
A23: OIC 13 | B23: Rimanenze.
A24: OIC 15 | B24: Crediti.
A25: OIC 16 | B25: Immobilizzazioni materiali.
A26: OIC 18 | B26: Ratei e risconti.
A27: OIC 19 | B27: Debiti.
A28: OIC 23 | B28: Lavori in corso su ordinazione.
A29: OIC 24 | B29: Immobilizzazioni immateriali.
A30: OIC 25 | B30: Imposte sul reddito (correnti, differite, anticipate).
A31: OIC 28 | B31: Patrimonio netto.
... A33: OIC 32 | B33: Strumenti finanziari derivati.
